setup.py
blended_disqus/__init__.py
blended_disqus.egg-info/PKG-INFO
blended_disqus.egg-info/SOURCES.txt
blended_disqus.egg-info/dependency_links.txt
blended_disqus.egg-info/not-zip-safe
blended_disqus.egg-info/requires.txt
blended_disqus.egg-info/top_level.txt